hrid/__init__.py
hrid/__version__.py
hrid/hrid.py
hrid/word_lists/__init__.py
hrid/word_lists/adjectives.py
hrid/word_lists/adverbs.py
hrid/word_lists/nouns.py
hrid/word_lists/verbs.py
hrid-0.3.1.dist-info/licenses/LICENSE
hrid-0.3.1.dist-info/METADATA
hrid-0.3.1.dist-info/WHEEL
hrid-0.3.1.dist-info/top_level.txt
hrid-0.3.1.dist-info/RECORD
